django_roughpages-0.3.0.dist-info/DESCRIPTION.rst
django_roughpages-0.3.0.dist-info/METADATA
django_roughpages-0.3.0.dist-info/RECORD
django_roughpages-0.3.0.dist-info/WHEEL
django_roughpages-0.3.0.dist-info/metadata.json
django_roughpages-0.3.0.dist-info/top_level.txt
django_roughpages-0.3.0.dist-info/zip-safe
roughpages/__init__.py
roughpages/compat.py
roughpages/conf.py
roughpages/middleware.py
roughpages/models.py
roughpages/utils.py
roughpages/views.py
roughpages/backends/__init__.py
roughpages/backends/auth.py
roughpages/backends/base.py
roughpages/backends/decorators.py
roughpages/backends/plain.py
roughpages/tests/__init__.py
roughpages/tests/compat.py
roughpages/tests/test_backends.py
roughpages/tests/test_middleware.py
roughpages/tests/test_utils.py
roughpages/tests/test_views.py
